[
  {
    "user_id": "U001",
    "name": "Aman",
    "viewed": ["P001", "P005", "P006"],
    "purchased": ["P001"],
    "preferences": {
      "categories": ["apparel", "cosmetics", "home_appliance"],
      "brands": ["Raymond", "Lakme", "Voltas"],
      "price_range": [500, 3000]
    }
  },
  {
    "user_id": "U002",
    "name": "Sneha",
    "viewed": ["P004", "P007", "P008"],
    "purchased": ["P004", "P007"],
    "preferences": {
      "categories": ["apparel", "home_appliance", "grocery"],
      "brands": ["Zara", "Usha", "Patanjali"],
      "price_range": [800, 3500]
    }
  },
  {
    "user_id": "U003",
    "name": "Ravi",
    "viewed": ["P002", "P009"],
    "purchased": [],
    "preferences": {
      "categories": ["accessories", "home_utility"],
      "brands": ["Flipkart Essentials", "Tupperware"],
      "price_range": [300, 1200]
    }
  },
  {
    "user_id": "U004",
    "name": "Meera",
    "viewed": ["P005", "P010"],
    "purchased": ["P005"],
    "preferences": {
      "categories": ["cosmetics", "electronics"],
      "brands": ["Lakme", "Eveready"],
      "price_range": [200, 1500]
    }
  },
  {
    "user_id": "U005",
    "name": "Ishaan",
    "viewed": ["P003", "P006", "P010"],
    "purchased": [],
    "preferences": {
      "categories": ["home_appliance", "electronics"],
      "brands": ["Bajaj", "Voltas", "Eveready"],
      "price_range": [1000, 4000]
    }
  },
  {
    "user_id": "U006",
    "name": "Diya",
    "viewed": ["P001", "P005"],
    "purchased": ["P005"],
    "preferences": {
      "categories": ["cosmetics", "apparel"],
      "brands": ["Lakme", "Raymond"],
      "price_range": [300, 1800]
    }
  },
  {
    "user_id": "U007",
    "name": "Kabir",
    "viewed": ["P006", "P007", "P009"],
    "purchased": ["P009"],
    "preferences": {
      "categories": ["home_appliance", "home_utility"],
      "brands": ["Voltas", "Usha", "Tupperware"],
      "price_range": [500, 5000]
    }
  },
  {
    "user_id": "U008",
    "name": "Ritika",
    "viewed": ["P005", "P002", "P004"],
    "purchased": ["P004"],
    "preferences": {
      "categories": ["apparel", "cosmetics", "accessories"],
      "brands": ["Zara", "Lakme", "Flipkart Essentials"],
      "price_range": [300, 2500]
    }
  },
  {
    "user_id": "U009",
    "name": "Yash",
    "viewed": ["P008", "P010"],
    "purchased": ["P010"],
    "preferences": {
      "categories": ["grocery", "electronics"],
      "brands": ["Eveready", "Patanjali"],
      "price_range": [200, 2000]
    }
  },
  {
    "user_id": "U010",
    "name": "Kavya",
    "viewed": ["P001", "P005", "P008"],
    "purchased": [],
    "preferences": {
      "categories": ["apparel", "grocery"],
      "brands": ["Raymond", "Patanjali"],
      "price_range": [300, 1500]
    }
  },
  {
    "user_id": "U011",
    "name": "Arjun",
    "viewed": ["P002", "P009", "P010"],
    "purchased": [],
    "preferences": {
      "categories": ["accessories", "home_utility", "electronics"],
      "brands": ["Eveready", "Tupperware"],
      "price_range": [300, 2000]
    }
  },
  {
    "user_id": "U012",
    "name": "Naina",
    "viewed": ["P005", "P006"],
    "purchased": [],
    "preferences": {
      "categories": ["cosmetics", "home_appliance"],
      "brands": ["Lakme", "Voltas"],
      "price_range": [200, 3000]
    }
  },
  {
    "user_id": "U013",
    "name": "Dev",
    "viewed": ["P003", "P010"],
    "purchased": ["P003"],
    "preferences": {
      "categories": ["home_appliance", "electronics"],
      "brands": ["Bajaj", "Eveready"],
      "price_range": [1000, 3500]
    }
  },
  {
    "user_id": "U014",
    "name": "Tanya",
    "viewed": ["P004", "P007"],
    "purchased": [],
    "preferences": {
      "categories": ["apparel", "home_appliance"],
      "brands": ["Zara", "Usha"],
      "price_range": [1000, 3000]
    }
  },
  {
    "user_id": "U015",
    "name": "Ansh",
    "viewed": ["P002", "P005"],
    "purchased": ["P002"],
    "preferences": {
      "categories": ["accessories", "cosmetics"],
      "brands": ["Flipkart Essentials", "Lakme"],
      "price_range": [200, 800]
    }
  },
  {
    "user_id": "U016",
    "name": "Shreya",
    "viewed": ["P001", "P006"],
    "purchased": [],
    "preferences": {
      "categories": ["apparel", "home_appliance"],
      "brands": ["Raymond", "Voltas"],
      "price_range": [1000, 2500]
    }
  },
  {
    "user_id": "U017",
    "name": "Rohit",
    "viewed": ["P003", "P007"],
    "purchased": [],
    "preferences": {
      "categories": ["home_appliance"],
      "brands": ["Bajaj", "Usha"],
      "price_range": [2000, 5000]
    }
  },
  {
    "user_id": "U018",
    "name": "Neha",
    "viewed": ["P005", "P008"],
    "purchased": ["P008"],
    "preferences": {
      "categories": ["cosmetics", "grocery"],
      "brands": ["Lakme", "Patanjali"],
      "price_range": [100, 1000]
    }
  },
  {
    "user_id": "U019",
    "name": "Harsh",
    "viewed": ["P002", "P009"],
    "purchased": [],
    "preferences": {
      "categories": ["home_utility", "accessories"],
      "brands": ["Tupperware", "Flipkart Essentials"],
      "price_range": [300, 1000]
    }
  },
  {
    "user_id": "U020",
    "name": "Sanya",
    "viewed": ["P001", "P004", "P006"],
    "purchased": ["P004"],
    "preferences": {
      "categories": ["apparel", "home_appliance"],
      "brands": ["Zara", "Voltas"],
      "price_range": [1000, 3500]
    }
  }
]
